{
  "meta": {
    "name": "スマ勢20-21",
    "year": "2020/06/01\n〜\n\n\n2021/05/30",
    "groupNum": "0604181448",
    "generation": "2018年生まれ"
  },
  "users": {
    "260436": {
      "name": "ヴィクトワールジタ",
      "money": 17689,
      "horses": [
        {
          "no": 1,
          "name": "サトノレイナス",
          "kettonum": "2018105179",
          "sex": "牝",
          "result": "[2-2-0-1]",
          "money": 10510,
          "syutoku": 4300,
          "stable": "国枝栄",
          "area": "美浦",
          "sire": "ディープインパクト",
          "dam": "バラダセール"
        },
        {
          "no": 4,
          "name": "レイオブウォーター",
          "kettonum": "2018104712",
          "sex": "牡",
          "result": "[3-2-2-8]",
          "money": 1380,
          "syutoku": 1500,
          "stable": "稲垣幸雄",
          "area": "美浦",
          "sire": "ディープインパクト",
          "dam": "ノーブルジュエリー"
        },
        {
          "no": 5,
          "name": "スワーヴエルメ",
          "kettonum": "2018104877",
          "sex": "牡",
          "result": "[3-3-1-1]",
          "money": 1330,
          "syutoku": 1500,
          "stable": "堀宣行",
          "area": "美浦",
          "sire": "ドゥラメンテ",
          "dam": "アイムユアーズ"
        },
        {
          "no": 8,
          "name": "グアドループ",
          "kettonum": "2018105283",
          "sex": "牡",
          "result": "[3-3-0-14]",
          "money": 1290,
          "syutoku": 900,
          "stable": "田村康仁",
          "area": "美浦",
          "sire": "ヴィクトワールピサ",
          "dam": "マンビア"
        },
        {
          "no": 9,
          "name": "マイプレシャス",
          "kettonum": "2018104616",
          "sex": "牡",
          "result": "[2-1-1-3]",
          "money": 891,
          "syutoku": 900,
          "stable": "松永幹夫",
          "area": "栗東",
          "sire": "ヴィクトワールピサ",
          "dam": "サラフィナ"
        },
        {
          "no": 6,
          "name": "ヘネラルカレーラ",
          "kettonum": "2018102718",
          "sex": "牝",
          "result": "[3-9-3-9]",
          "money": 817,
          "syutoku": 1500,
          "stable": "角田晃一",
          "area": "栗東",
          "sire": "キズナ",
          "dam": "セレブラール"
        },
        {
          "no": 2,
          "name": "サンデージャック",
          "kettonum": "2018105260",
          "sex": "牡",
          "result": "[2-1-4-24]",
          "money": 710,
          "syutoku": 900,
          "stable": "宮本博",
          "area": "栗東",
          "sire": "ダイワメジャー",
          "dam": "ホットチャチャ"
        },
        {
          "no": 10,
          "name": "ララパピヨンドメル",
          "kettonum": "2018105805",
          "sex": "牝",
          "result": "[0-2-5-19]",
          "money": 580,
          "syutoku": 0,
          "stable": "大竹正博",
          "area": "美浦",
          "sire": "ヴィクトワールピサ",
          "dam": "ウィストラム"
        },
        {
          "no": 3,
          "name": "ヴェックマン",
          "kettonum": "2018105281",
          "sex": "牡",
          "result": "[0-0-1-1]",
          "money": 130,
          "syutoku": 0,
          "stable": "音無秀孝",
          "area": "栗東",
          "sire": "ミッキーアイル",
          "dam": "マルティンスターク"
        },
        {
          "no": 7,
          "name": "リュラネブラ",
          "kettonum": "2018105346",
          "sex": "牡",
          "result": "[0-0-0-20]",
          "money": 51,
          "syutoku": 0,
          "stable": "国枝栄",
          "area": "美浦",
          "sire": "ロードカナロア",
          "dam": "リュラ"
        }
      ]
    },
    "260437": {
      "name": "ステゴ",
      "money": 31674,
      "horses": [
        {
          "no": 10,
          "name": "グレナディアガーズ",
          "kettonum": "2018104934",
          "sex": "牡",
          "result": "[3-4-2-7]",
          "money": 11967,
          "syutoku": 10700,
          "stable": "中内田充",
          "area": "栗東",
          "sire": "Frankel",
          "dam": "ウェイヴェルアベニュー"
        },
        {
          "no": 2,
          "name": "レッドジェネシス",
          "kettonum": "2018105343",
          "sex": "セ",
          "result": "[3-1-2-13]",
          "money": 7307,
          "syutoku": 4700,
          "stable": "小林真也",
          "area": "栗東",
          "sire": "ディープインパクト",
          "dam": "リュズキナ"
        },
        {
          "no": 1,
          "name": "レッドベルオーブ",
          "kettonum": "2018105366",
          "sex": "牡",
          "result": "[3-1-2-19]",
          "money": 6390,
          "syutoku": 3500,
          "stable": "河嶋宏樹",
          "area": "栗東",
          "sire": "ディープインパクト",
          "dam": "レッドファンタジア"
        },
        {
          "no": 6,
          "name": "カランドゥーラ",
          "kettonum": "2018105321",
          "sex": "牡",
          "result": "[3-4-3-14]",
          "money": 1731,
          "syutoku": 1500,
          "stable": "福永祐一",
          "area": "栗東",
          "sire": "モーリス",
          "dam": "ラストグルーヴ"
        },
        {
          "no": 5,
          "name": "ローウェル",
          "kettonum": "2018105470",
          "sex": "セ",
          "result": "[4-4-2-6]",
          "money": 1420,
          "syutoku": 1500,
          "stable": "斉藤崇史",
          "area": "栗東",
          "sire": "キズナ",
          "dam": "アンティフォナ"
        },
        {
          "no": 3,
          "name": "サトノスカイターフ",
          "kettonum": "2018105073",
          "sex": "牡",
          "result": "[2-7-6-24]",
          "money": 1280,
          "syutoku": 900,
          "stable": "池江泰寿",
          "area": "栗東",
          "sire": "ディープインパクト",
          "dam": "シーヴ"
        },
        {
          "no": 8,
          "name": "パタゴニア",
          "kettonum": "2018105314",
          "sex": "牝",
          "result": "[2-0-2-13]",
          "money": 831,
          "syutoku": 900,
          "stable": "池添学",
          "area": "栗東",
          "sire": "キズナ",
          "dam": "ライフフォーセール"
        },
        {
          "no": 9,
          "name": "オブデュモンド",
          "kettonum": "2018102202",
          "sex": "セ",
          "result": "[2-4-3-16]",
          "money": 658,
          "syutoku": 900,
          "stable": "蛯名正義",
          "area": "美浦",
          "sire": "ドゥラメンテ",
          "dam": "クイーンオブトロイ"
        },
        {
          "no": 7,
          "name": "レアリサンド",
          "kettonum": "2018106253",
          "sex": "牡",
          "result": "[0-0-0-3]",
          "money": 90,
          "syutoku": 0,
          "stable": "高野友和",
          "area": "栗東",
          "sire": "ディープインパクト",
          "dam": "ドリームオブジェニー"
        },
        {
          "no": 4,
          "name": "トレジャーアイル",
          "kettonum": "2018105111",
          "sex": "牡",
          "result": "[0-0-0-1]",
          "money": 0,
          "syutoku": 0,
          "stable": "宮田敬介",
          "area": "美浦",
          "sire": "ミッキーアイル",
          "dam": "スーヴェニアギフト"
        }
      ]
    },
    "260438": {
      "name": "ﾀﾞｲﾜふにゃ～ﾚｯﾄ",
      "money": 31851,
      "horses": [
        {
          "no": 8,
          "name": "ステラヴェローチェ",
          "kettonum": "2018104980",
          "sex": "牡",
          "result": "[4-2-3-10]",
          "money": 14980,
          "syutoku": 8650,
          "stable": "須貝尚介",
          "area": "栗東",
          "sire": "バゴ",
          "dam": "オーマイベイビー"
        },
        {
          "no": 2,
          "name": "ヨーホーレイク",
          "kettonum": "2018105012",
          "sex": "牡",
          "result": "[5-1-5-7]",
          "money": 6110,
          "syutoku": 9750,
          "stable": "友道康夫",
          "area": "栗東",
          "sire": "ディープインパクト",
          "dam": "クロウキャニオン"
        },
        {
          "no": 1,
          "name": "ルペルカーリア",
          "kettonum": "2018105076",
          "sex": "牡",
          "result": "[2-1-1-8]",
          "money": 3390,
          "syutoku": 2400,
          "stable": "友道康夫",
          "area": "栗東",
          "sire": "モーリス",
          "dam": "シーザリオ"
        },
        {
          "no": 3,
          "name": "レガトゥス",
          "kettonum": "2018104896",
          "sex": "セ",
          "result": "[4-1-4-12]",
          "money": 1740,
          "syutoku": 2400,
          "stable": "矢嶋大樹",
          "area": "美浦",
          "sire": "モーリス",
          "dam": "アドマイヤセプター"
        },
        {
          "no": 7,
          "name": "ドゥラモンド",
          "kettonum": "2018105078",
          "sex": "牡",
          "result": "[5-5-2-19]",
          "money": 1710,
          "syutoku": 1500,
          "stable": "手塚貴久",
          "area": "美浦",
          "sire": "ドゥラメンテ",
          "dam": "シーズインクルーデッド"
        },
        {
          "no": 9,
          "name": "アップリバー",
          "kettonum": "2018105004",
          "sex": "牝",
          "result": "[3-4-5-16]",
          "money": 1608,
          "syutoku": 1500,
          "stable": "牧光二",
          "area": "美浦",
          "sire": "スクリーンヒーロー",
          "dam": "クイーンビー２"
        },
        {
          "no": 5,
          "name": "シテフローラル",
          "kettonum": "2018105086",
          "sex": "セ",
          "result": "[2-4-1-17]",
          "money": 1267,
          "syutoku": 900,
          "stable": "堀宣行",
          "area": "美浦",
          "sire": "ディープインパクト",
          "dam": "ジョコンダ２"
        },
        {
          "no": 10,
          "name": "ラピカズマ",
          "kettonum": "2018105357",
          "sex": "牡",
          "result": "[1-3-2-25]",
          "money": 815,
          "syutoku": 400,
          "stable": "高橋文雅",
          "area": "美浦",
          "sire": "キンシャサノキセキ",
          "dam": "レイズアンドコール"
        },
        {
          "no": 4,
          "name": "サヴァニャン",
          "kettonum": "2018105041",
          "sex": "牝",
          "result": "[0-0-1-7]",
          "money": 180,
          "syutoku": 0,
          "stable": "藤原英昭",
          "area": "栗東",
          "sire": "ディープインパクト",
          "dam": "サマーハ"
        },
        {
          "no": 6,
          "name": "ザレストノーウェア",
          "kettonum": "2018105291",
          "sex": "牡",
          "result": "[1-1-3-17]",
          "money": 51,
          "syutoku": 0,
          "stable": "新開幸一",
          "area": "美浦",
          "sire": "ディープインパクト",
          "dam": "ミュージカルウェイ"
        }
      ]
    },
    "260439": {
      "name": "ファミブラヴ",
      "money": 5307,
      "horses": [
        {
          "no": 3,
          "name": "ディオスバリエンテ",
          "kettonum": "2018105147",
          "sex": "セ",
          "result": "[4-6-3-12]",
          "money": 1500,
          "syutoku": 2400,
          "stable": "堀宣行",
          "area": "美浦",
          "sire": "ロードカナロア",
          "dam": "ディアデラノビア"
        },
        {
          "no": 1,
          "name": "アークライト",
          "kettonum": "2018105193",
          "sex": "牡",
          "result": "[0-4-2-5]",
          "money": 1061,
          "syutoku": 0,
          "stable": "藤沢和雄",
          "area": "美浦",
          "sire": "ディープインパクト",
          "dam": "ヒストリックスター"
        },
        {
          "no": 6,
          "name": "エクスインパクト",
          "kettonum": "2018104957",
          "sex": "セ",
          "result": "[1-2-1-10]",
          "money": 657,
          "syutoku": 400,
          "stable": "尾関知人",
          "area": "美浦",
          "sire": "ディープインパクト",
          "dam": "エクセレンス２"
        },
        {
          "no": 10,
          "name": "マンインザミラー",
          "kettonum": "2018105066",
          "sex": "牡",
          "result": "[1-1-1-7]",
          "money": 600,
          "syutoku": 400,
          "stable": "池江泰寿",
          "area": "栗東",
          "sire": "ディープインパクト",
          "dam": "シルヴァースカヤ"
        },
        {
          "no": 4,
          "name": "クライミングリリー",
          "kettonum": "2018104607",
          "sex": "牝",
          "result": "[3-3-1-9]",
          "money": 510,
          "syutoku": 1500,
          "stable": "国枝栄",
          "area": "美浦",
          "sire": "ディープインパクト",
          "dam": "コンテスティッド"
        },
        {
          "no": 5,
          "name": "ヴェルナー",
          "kettonum": "2018104889",
          "sex": "牡",
          "result": "[1-1-1-3]",
          "money": 491,
          "syutoku": 0,
          "stable": "高野友和",
          "area": "栗東",
          "sire": "キングカメハメハ",
          "dam": "アディクティド"
        },
        {
          "no": 8,
          "name": "ミッキーセレスタ",
          "kettonum": "2018105116",
          "sex": "牡",
          "result": "[0-1-0-9]",
          "money": 187,
          "syutoku": 0,
          "stable": "国枝栄",
          "area": "美浦",
          "sire": "ハーツクライ",
          "dam": "セレスタ"
        },
        {
          "no": 7,
          "name": "ポルトヴェッキオ",
          "kettonum": "2018105266",
          "sex": "牝",
          "result": "[3-3-2-3]",
          "money": 180,
          "syutoku": 630,
          "stable": "田中博康",
          "area": "美浦",
          "sire": "ロードカナロア",
          "dam": "ポルトフィーノ"
        },
        {
          "no": 2,
          "name": "トレデマンド",
          "kettonum": "2018105035",
          "sex": "牝",
          "result": "[2-2-0-15]",
          "money": 121,
          "syutoku": 900,
          "stable": "松永幹夫",
          "area": "栗東",
          "sire": "ディープインパクト",
          "dam": "コンドコマンド"
        },
        {
          "no": 9,
          "name": "リエヴェメンテ",
          "kettonum": "2018105196",
          "sex": "牝",
          "result": "[0-0-0-4]",
          "money": 0,
          "syutoku": 0,
          "stable": "萩原清",
          "area": "美浦",
          "sire": "ドゥラメンテ",
          "dam": "ヒルダズパッション"
        }
      ]
    },
    "260440": {
      "name": "競馬勢のＳｙｍｋ",
      "money": 8751,
      "horses": [
        {
          "no": 7,
          "name": "オーソクレース",
          "kettonum": "2018105280",
          "sex": "牡",
          "result": "[2-2-1-1]",
          "money": 5200,
          "syutoku": 5000,
          "stable": "久保田貴",
          "area": "美浦",
          "sire": "エピファネイア",
          "dam": "マリアライト"
        },
        {
          "no": 8,
          "name": "グレイイングリーン",
          "kettonum": "2018105454",
          "sex": "牡",
          "result": "[5-4-4-26]",
          "money": 1610,
          "syutoku": 3800,
          "stable": "池江泰寿",
          "area": "栗東",
          "sire": "ディープインパクト",
          "dam": "リトルゲルダ"
        },
        {
          "no": 9,
          "name": "ノックオンウッド",
          "kettonum": "2018103920",
          "sex": "セ",
          "result": "[2-3-1-10]",
          "money": 940,
          "syutoku": 900,
          "stable": "堀宣行",
          "area": "美浦",
          "sire": "Frankel",
          "dam": "トゥアーニー"
        },
        {
          "no": 4,
          "name": "セブンサミット",
          "kettonum": "2018105071",
          "sex": "牡",
          "result": "[3-3-5-8]",
          "money": 491,
          "syutoku": 1600,
          "stable": "西村真幸",
          "area": "栗東",
          "sire": "モーリス",
          "dam": "シンハライト"
        },
        {
          "no": 2,
          "name": "アルマドラード",
          "kettonum": "2018105328",
          "sex": "セ",
          "result": "[2-2-2-13]",
          "money": 240,
          "syutoku": 900,
          "stable": "小笠倫弘",
          "area": "美浦",
          "sire": "キングカメハメハ",
          "dam": "ラドラーダ"
        },
        {
          "no": 3,
          "name": "メイレンシュタイン",
          "kettonum": "2018105476",
          "sex": "セ",
          "result": "[1-1-1-14]",
          "money": 200,
          "syutoku": 400,
          "stable": "勢司和浩",
          "area": "美浦",
          "sire": "エピファネイア",
          "dam": "ヴァイスゴルト"
        },
        {
          "no": 6,
          "name": "ギルティブラック",
          "kettonum": "2018104926",
          "sex": "牡",
          "result": "[0-1-0-5]",
          "money": 70,
          "syutoku": 0,
          "stable": "安田隆行",
          "area": "栗東",
          "sire": "ディープインパクト",
          "dam": "インナーレルム"
        },
        {
          "no": 1,
          "name": "ガルフォート",
          "kettonum": "2018105267",
          "sex": "牡",
          "result": "[0-0-0-8]",
          "money": 0,
          "syutoku": 0,
          "stable": "中内田充",
          "area": "栗東",
          "sire": "ディープインパクト",
          "dam": "ポロンナルワ"
        },
        {
          "no": 5,
          "name": "チャップマン",
          "kettonum": "2018104993",
          "sex": "牡",
          "result": "[0-0-0-2]",
          "money": 0,
          "syutoku": 0,
          "stable": "奥村豊",
          "area": "栗東",
          "sire": "リオンディーズ",
          "dam": "ガラシア"
        },
        {
          "no": 10,
          "name": "ラヴドワンズ",
          "kettonum": "2018105149",
          "sex": "牝",
          "result": "[0-0-0-4]",
          "money": 0,
          "syutoku": 0,
          "stable": "宮田敬介",
          "area": "美浦",
          "sire": "リオンディーズ",
          "dam": "ディアマイベイビー"
        }
      ]
    },
    "260441": {
      "name": "ｴﾙｺﾝﾄﾞﾙｽﾊﾟｲｼｰ",
      "money": 17210,
      "horses": [
        {
          "no": 2,
          "name": "アカイトリノムスメ",
          "kettonum": "2018104903",
          "sex": "牝",
          "result": "[4-1-0-3]",
          "money": 11020,
          "syutoku": 9850,
          "stable": "国枝栄",
          "area": "美浦",
          "sire": "ディープインパクト",
          "dam": "アパパネ"
        },
        {
          "no": 4,
          "name": "アンブレラデート",
          "kettonum": "2018104664",
          "sex": "牝",
          "result": "[2-2-0-7]",
          "money": 1770,
          "syutoku": 900,
          "stable": "藤原英昭",
          "area": "栗東",
          "sire": "エイシンフラッシュ",
          "dam": "ダイワスカーレット"
        },
        {
          "no": 6,
          "name": "クリーンスイープ",
          "kettonum": "2018105090",
          "sex": "牝",
          "result": "[3-2-0-2]",
          "money": 1190,
          "syutoku": 1500,
          "stable": "国枝栄",
          "area": "美浦",
          "sire": "ドゥラメンテ",
          "dam": "スイープトウショウ"
        },
        {
          "no": 8,
          "name": "トーセンマッシモ",
          "kettonum": "2018104117",
          "sex": "セ",
          "result": "[8-4-2-18]",
          "money": 1040,
          "syutoku": 1100,
          "stable": "小野次郎",
          "area": "美浦",
          "sire": "キングカメハメハ",
          "dam": "ホエールキャプチャ"
        },
        {
          "no": 7,
          "name": "ジェラルディーナ",
          "kettonum": "2018105081",
          "sex": "牝",
          "result": "[6-2-3-12]",
          "money": 890,
          "syutoku": 13100,
          "stable": "斉藤崇史",
          "area": "栗東",
          "sire": "モーリス",
          "dam": "ジェンティルドンナ"
        },
        {
          "no": 1,
          "name": "ブエナベントゥーラ",
          "kettonum": "2018105232",
          "sex": "牡",
          "result": "[1-1-1-6]",
          "money": 790,
          "syutoku": 400,
          "stable": "堀宣行",
          "area": "美浦",
          "sire": "モーリス",
          "dam": "ブエナビスタ"
        },
        {
          "no": 5,
          "name": "ディヴィーナ",
          "kettonum": "2018104947",
          "sex": "牝",
          "result": "[5-3-2-10]",
          "money": 510,
          "syutoku": 6750,
          "stable": "友道康夫",
          "area": "栗東",
          "sire": "モーリス",
          "dam": "ヴィルシーナ"
        },
        {
          "no": 3,
          "name": "アレスクラー",
          "kettonum": "2018104882",
          "sex": "牡",
          "result": "[0-0-0-5]",
          "money": 0,
          "syutoku": 0,
          "stable": "音無秀孝",
          "area": "栗東",
          "sire": "ロードカナロア",
          "dam": "アゲヒバリ"
        },
        {
          "no": 9,
          "name": "",
          "kettonum": "",
          "sex": "",
          "result": "[0-0-0-0]",
          "money": 0,
          "syutoku": 0,
          "stable": "",
          "area": "",
          "sire": "",
          "dam": "ニコマル"
        },
        {
          "no": 10,
          "name": "ヤサカキングチャン",
          "kettonum": "2018101599",
          "sex": "牡",
          "result": "[0-0-0-2]",
          "money": 0,
          "syutoku": 0,
          "stable": "水野貴広",
          "area": "美浦",
          "sire": "アジアエクスプレス",
          "dam": "ヤサカシャイニー"
        }
      ]
    }
  }
}